[{"id":2,"programId":1,"title":"Match a variable against string literals to decide which command to run:","rawContent":"case {{$tocount}} in {{words}}) {{wc -w README}}; ;; {{lines}}) {{wc -l README}}; ;; esac"},{"id":3,"programId":1,"title":"Combine patterns with |, use * as a fallback pattern:","rawContent":"case {{$tocount}} in {{[wW]|words}}) {{wc -w README}}; ;; {{[lL]|lines}}) {{wc -l README}}; ;; *) {{echo \"what?\"}}; ;; esac"},{"id":4,"programId":2,"title":"Remove spaces and other undesirable characters from a file's name:","rawContent":"detox {{file}}"},{"id":5,"programId":2,"title":"Show how detox would rename all of the files in a directory tree:","rawContent":"detox --dry-run -r {{directory}}"},{"id":6,"programId":2,"title":"Remove spaces and other undesirable characters from all files in a directory tree:","rawContent":"detox -r {{directory}}"},{"id":7,"programId":3,"title":"View reflog:","rawContent":"git reflog"},{"id":8,"programId":3,"title":"View 5 latest entries in reflog:","rawContent":"git reflog -n {{5}}"},{"id":9,"programId":4,"title":"View a summary of all the commits made, grouped alphabetically by author name:","rawContent":"git shortlog"},{"id":10,"programId":4,"title":"View a summary of all the commits made, sorted by the number of commits made:","rawContent":"git shortlog -n"},{"id":11,"programId":4,"title":"View a summary of all the commits made, grouped by the commiter identities (name and email):","rawContent":"git shortlog -c"},{"id":12,"programId":4,"title":"View a summary of the last 5 commits (i.e. specify a revision range):","rawContent":"git shortlog HEAD~{{5}}..HEAD"},{"id":13,"programId":5,"title":"Report only statistics that have a level of concern greater than 0:","rawContent":"git sizer"},{"id":14,"programId":5,"title":"Report all statistics:","rawContent":"git sizer -v"},{"id":15,"programId":5,"title":"See additional options:","rawContent":"git sizer -h"},{"id":16,"programId":6,"title":"Show the repository browser for the current git repository:","rawContent":"gitk"},{"id":17,"programId":6,"title":"Show repository browser for a specific file or folder:","rawContent":"gitk {{path/to/file_or_folder}}"},{"id":18,"programId":6,"title":"Show commits made since 1 week ago:","rawContent":"gitk --since={{\"1 week ago\"}}"},{"id":19,"programId":6,"title":"Show commits older than 1/1/2016:","rawContent":"gitk --until={{\"1/1/2015\"}}"},{"id":20,"programId":6,"title":"Show at most 100 changes in all branches:","rawContent":" gitk --max-count={{100}} --all"},{"id":21,"programId":7,"title":"Synchronize imap account between host1 and host2:","rawContent":"imapsync --host1 {{host1}} --user1 {{user1}} --password1 {{secret1}} --host2 {{host2}} --user2 {{user2}} --password2 {{secret2}}"},{"id":22,"programId":8,"title":"Convert JSON5 stdin to JSON stdout:","rawContent":"echo {{input}} | json5"},{"id":23,"programId":8,"title":"Convert a JSON5 file to JSON and output to stdout:","rawContent":"json5 {{path/to/input_file.json5}}"},{"id":24,"programId":8,"title":"Convert a JSON5 file to the specified JSON file:","rawContent":"json5 {{path/to/input_file.json5}} --out-file {{path/to/output_file.json}}"},{"id":25,"programId":8,"title":"Validate a JSON5 file:","rawContent":"json5 {{path/to/input_file.json5}} --validate"},{"id":26,"programId":8,"title":"Specify the number of spaces to indent by (or \"t\" for tabs):","rawContent":"json5 --space {{indent_amount}}"},{"id":27,"programId":8,"title":"View available options:","rawContent":"json5 --help"},{"id":28,"programId":9,"title":"Open a file and enter normal mode, to execute commands:","rawContent":"kak {{path/to/file}}"},{"id":29,"programId":9,"title":"Enter insert mode from normal mode, to write text into the file:","rawContent":"i"},{"id":30,"programId":9,"title":"Escape insert mode, to go back to normal mode:","rawContent":"<Escape>"},{"id":31,"programId":9,"title":"Replace all instances of \"foo\" in the current file with \"bar\":","rawContent":"%s{{foo}}<Enter>c{{bar}}<Escape>"},{"id":32,"programId":9,"title":"Un-select all secondary selections, and keep only the main one:","rawContent":"<Space>"},{"id":33,"programId":9,"title":"Search for numbers and select the first two:","rawContent":"/\\d+<Enter>N"},{"id":34,"programId":9,"title":"Insert the contents of a file:","rawContent":"!cat {{path/to/file}}<Enter>"},{"id":35,"programId":9,"title":"Save the current file:","rawContent":":w<Enter>"},{"id":36,"programId":10,"title":"Create a new Laravel application:","rawContent":"laravel new {{name}}"},{"id":37,"programId":10,"title":"Use the latest development release:","rawContent":"laravel new {{name}} --dev"},{"id":38,"programId":10,"title":"Overwrite if the directory already exists:","rawContent":"laravel new {{name}} --force"},{"id":39,"programId":10,"title":"List the available installer commands:","rawContent":"laravel list"},{"id":40,"programId":11,"title":"Install one or more packages:","rawContent":"omf install {{name}}"},{"id":41,"programId":11,"title":"List installed packages:","rawContent":"omf list"},{"id":42,"programId":11,"title":"List available themes:","rawContent":"omf theme"},{"id":43,"programId":11,"title":"Apply a theme:","rawContent":"omf theme {{name}}"},{"id":44,"programId":11,"title":"Remove a theme or package:","rawContent":"omf remove {{name}}"},{"id":45,"programId":11,"title":"Uninstall Oh My Fish:","rawContent":"omf destroy"},{"id":46,"programId":12,"title":"Merge two PDFs:","rawContent":"pdfjoin {{file1}} {{file2}} --outfile {{output_file}}"},{"id":47,"programId":12,"title":"Save pages 3 to 5 followed by page 1 to a new PDF:","rawContent":"pdfjoin {{file 3-5,1}} --outfile {{output_file}}"},{"id":48,"programId":12,"title":"Merge subranges from two PDFs:","rawContent":"pdfjoin {{file1 3-5,1}} {{file2 4-6}} --outfile {{output_file}}"},{"id":49,"programId":13,"title":"Analyse a directory and print the result:","rawContent":"phploc {{path/to/directory}}"},{"id":50,"programId":13,"title":"Include only specific files from a comma-separated list (globs are allowed):","rawContent":"phploc {{path/to/directory}} --names {{files}}"},{"id":51,"programId":13,"title":"Exclude specific files from a comma-separated list (globs are allowed):","rawContent":"phploc {{path/to/directory}} --names-exclude {{files}}"},{"id":52,"programId":13,"title":"Exclude a specific directory from analysis:","rawContent":"phploc {{path/to/directory}} --exclude {{path/to/exclude_directory}}"},{"id":53,"programId":13,"title":"Log the results to a specific CSV file:","rawContent":"phploc {{path/to/directory}} --log-csv {{path/to/file}}"},{"id":54,"programId":13,"title":"Log the results to a specific XML file:","rawContent":"phploc {{path/to/directory}} --log-xml {{path/to/file}}"},{"id":55,"programId":13,"title":"Count PHPUnit test case classes and test methods:","rawContent":"phploc {{path/to/directory}} --count-tests"},{"id":56,"programId":14,"title":"Display available options for analysis:","rawContent":"phpstan analyse --help"},{"id":57,"programId":14,"title":"Analyse the specified space-separated directories:","rawContent":"phpstan analyse {{path/to/directory}}"},{"id":58,"programId":14,"title":"Analyse a directory using a configuration file:","rawContent":"phpstan analyse {{path/to/directory}} --configuration {{path/to/config}}"},{"id":59,"programId":14,"title":"Analyse using a specific rule level (0-7, higher is stricter):","rawContent":"phpstan analyse {{path/to/directory}} --level {{level}}"},{"id":60,"programId":14,"title":"Specify an autoload file to load before analysing:","rawContent":"phpstan analyse {{path/to/directory}} --autoload-file {{path/to/autoload_file}}"},{"id":61,"programId":14,"title":"Specify a memory limit during analysis:","rawContent":"phpstan analyse {{path/to/directory}} --memory-limit {{memory_limit}}"},{"id":62,"programId":15,"title":"Do a dry-run renaming a folder of pngs with a literal string replacement:","rawContent":"repren --dry-run --rename --literal --from '{{find_string}}' --to '{{replacement_string}}' {{*.png}}"},{"id":63,"programId":15,"title":"Do a dry-run renaming a folder of jpegs with a regular expression:","rawContent":"repren --rename --dry-run --from '{{regular_expression}}' --to '{{replacement_string}}' {{*.jpg}} {{*.jpeg}}"},{"id":64,"programId":15,"title":"Do a find-and-replace on the contents of a folder of csv files:","rawContent":"repren --from '{{([0-9]+) example_string}}' --to '{{replacement_string \\1}}' {{*.csv}}"},{"id":65,"programId":15,"title":"Do both a find-and-replace and a rename operation at the same time, using a pattern file:","rawContent":"repren --patterns {{path/to/patfile.ext}} --full {{*.txt}}"},{"id":66,"programId":15,"title":"Do a case-insensitive rename:","rawContent":"repren --rename --insensitive --patterns {{path/to/patfile.ext}} *"},{"id":67,"programId":16,"title":"Install one or more space-separated versions of Ruby:","rawContent":"rvm install {{version(s)}}"},{"id":68,"programId":16,"title":"Display a list of installed versions:","rawContent":"rvm list"},{"id":69,"programId":16,"title":"Use a specific version of Ruby:","rawContent":"rvm use {{version}}"},{"id":70,"programId":16,"title":"Set the default Ruby version:","rawContent":"rvm --default use {{version}}"},{"id":71,"programId":16,"title":"Upgrade a version of Ruby to a new version:","rawContent":"rvm upgrade {{current_version}} {{new_version}}"},{"id":72,"programId":16,"title":"Uninstall a version of Ruby and keep its sources:","rawContent":"rvm uninstall {{version}}"},{"id":73,"programId":16,"title":"Remove a version of Ruby and its sources:","rawContent":"rvm remove {{version}}"},{"id":74,"programId":17,"title":"Compress executable:","rawContent":"upx {{file}}"},{"id":75,"programId":17,"title":"Decompress executable:","rawContent":"upx -d {{file}}"},{"id":76,"programId":17,"title":"Detailed help:","rawContent":"upx --help"},{"id":77,"programId":18,"title":"Display the current configuration (or dry run):","rawContent":"authconfig --test"},{"id":78,"programId":18,"title":"Configure the server to use a different password hashing algorithm:","rawContent":"authconfig --update --passalgo={{algorithm}}"},{"id":79,"programId":18,"title":"Enable LDAP authentication:","rawContent":"authconfig --update --enableldapauth"},{"id":80,"programId":18,"title":"Disable LDAP authentication:","rawContent":"authconfig --update --disableldapauth"},{"id":81,"programId":18,"title":"Enable Network Information Service (NIS):","rawContent":"authconfig --update --enablenis"},{"id":82,"programId":18,"title":"Enable Kerberos:","rawContent":"authconfig --update --enablekrb5"},{"id":83,"programId":18,"title":"Enable Winbind (Active Directory) authentication:","rawContent":"authconfig --update --enablewinbindauth"},{"id":84,"programId":18,"title":"Enable local authorization:","rawContent":"authconfig --update --enablelocauthorize"},{"id":85,"programId":19,"title":"Obtain a new certificate via webroot authorization, but do not install it automatically:","rawContent":"sudo certbot certonly --webroot --webroot-path {{path/to/webroot}} --domain {{subdomain.example.com}}"},{"id":86,"programId":19,"title":"Obtain a new certificate via nginx authorization, installing the new certificate automatically:","rawContent":"sudo certbot --nginx --domain {{subdomain.example.com}}"},{"id":87,"programId":19,"title":"Obtain a new certificate via apache authorization, installing the new certificate automatically:","rawContent":"sudo certbot --apache --domain {{subdomain.example.com}}"},{"id":88,"programId":19,"title":"Renew all Let's Encrypt certificates that in 30 days or less (don't forget to restart any servers that use them afterwards):","rawContent":"sudo certbot renew"},{"id":89,"programId":19,"title":"Simulate the obtaining of a new certificate, but don't actually save any new certificates to disk:","rawContent":"sudo certbot --webroot --webroot-path {{path/to/webroot}} --domain {{subdomain.example.com}} --dry-run"},{"id":90,"programId":19,"title":"Obtain an untrusted test certificate instead:","rawContent":"sudo certbot --webroot --webroot-path {{path/to/webroot}} --domain {{subdomain.example.com}} --test-cert"},{"id":91,"programId":20,"title":"List all commands that you could run:","rawContent":"compgen -c"},{"id":92,"programId":20,"title":"List all aliases:","rawContent":"compgen -a"},{"id":93,"programId":20,"title":"List all functions that you could run:","rawContent":"compgen -A function"},{"id":94,"programId":20,"title":"Show shell reserved key words:","rawContent":"compgen -k"},{"id":95,"programId":20,"title":"See all available commands/aliases starting with 'ls':","rawContent":"compgen -ac {{ls}}"},{"id":96,"programId":21,"title":"Open a new VPN connection:","rawContent":"f5fpc --start"},{"id":97,"programId":21,"title":"Open a new VPN connection to a specific host:","rawContent":"f5fpc --start --host {{host.example.com}}"},{"id":98,"programId":21,"title":"Specify a username (user will be prompted for a password):","rawContent":"f5fpc --start --host {{host.example.com}} --username {{user}}"},{"id":99,"programId":21,"title":"Show the current VPN status:","rawContent":"f5fpc --info"},{"id":100,"programId":21,"title":"Shutdown the VPN connection:","rawContent":"f5fpc --stop"},{"id":101,"programId":22,"title":"List partitions:","rawContent":"fdisk -l"},{"id":102,"programId":22,"title":"Start the partition manipulator:","rawContent":"fdisk {{/dev/sda}}"},{"id":103,"programId":23,"title":"Print the hexadecimal representation of a file:","rawContent":"hexdump {{file}}"},{"id":104,"programId":23,"title":"Display the input offset in hexadecimal and its ASCII representation in two columns:","rawContent":"hexdump -C {{file}}"},{"id":105,"programId":23,"title":"Display the hexadecimal representation of a file, but interpret only n bytes of the input:","rawContent":"hexdump -C -n{{number_of_bytes}} {{file}}"},{"id":106,"programId":24,"title":"Install a package:","rawContent":"opkg install {{package}}"},{"id":107,"programId":24,"title":"Remove a package:","rawContent":"opkg remove {{package}}"},{"id":108,"programId":24,"title":"Update the list of available packages:","rawContent":"opkg update"},{"id":109,"programId":24,"title":"Upgrade all the installed packages:","rawContent":"opkg upgrade"},{"id":110,"programId":24,"title":"Upgrade one or more specific package(s):","rawContent":"opkg upgrade {{package(s)}}"},{"id":111,"programId":24,"title":"Display informations for a specific package:","rawContent":"opkg info {{package}}"},{"id":112,"programId":24,"title":"List all the available packages:","rawContent":"opkg list"},{"id":113,"programId":25,"title":"Add space-separated files or directories to a Phar file:","rawContent":"phar add -f {{path/to/phar_file}} {{files_or_directories}}"},{"id":114,"programId":25,"title":"Display the contents of a Phar file:","rawContent":"phar list -f {{path/to/phar_file}}"},{"id":115,"programId":25,"title":"Delete the specified file or directory from a Phar file:","rawContent":"phar delete -f {{path/to/phar_file}} -e {{file_or_directory}}"},{"id":116,"programId":25,"title":"Display full usage information and available hashing/compression algorithms:","rawContent":"phar help"},{"id":117,"programId":25,"title":"Compress or uncompress files and directories in a Phar file:","rawContent":"phar compress -f {{path/to/phar_file}} -c {{algorithm}}"},{"id":118,"programId":25,"title":"Get information about a Phar file:","rawContent":"phar info -f {{path/to/phar_file}}"},{"id":119,"programId":25,"title":"Sign a Phar file with a specific hash algorithm:","rawContent":"phar sign -f {{path/to/phar_file}} -h {{algorithm}}"},{"id":120,"programId":25,"title":"Sign a Phar file with an OpenSSL private key:","rawContent":"phar sign -f {{path/to/phar_file}} -h openssl -y {{path/to/private_key}}"},{"id":121,"programId":26,"title":"Run in interactive mode:","rawContent":"units"},{"id":122,"programId":26,"title":"Show the conversion between two simple units:","rawContent":"units {{quarts}} {{tablespoons}}"},{"id":123,"programId":26,"title":"Convert between units with quantities:","rawContent":"units {{15 pounds}} {{kilograms}}"},{"id":124,"programId":26,"title":"Show the conversion between two compound units:","rawContent":"units {{\"meters / second\"}} {{\"inches / hour\"}}"},{"id":125,"programId":26,"title":"Show the conversion between units with different dimensions:","rawContent":"units {{\"acres\"}} {{\"ft^2\"}}"},{"id":126,"programId":27,"title":"View an image:","rawContent":"viewnior {{path/to/image.ext}}"},{"id":127,"programId":27,"title":"View in fullscreen mode:","rawContent":"viewnior --fullscreen {{path/to/image.ext}}"},{"id":128,"programId":27,"title":"View fullscreen in slideshow mode:","rawContent":"viewnior --slideshow {{path/to/image.ext}}"},{"id":129,"programId":28,"title":"Yank using the default delimiters (\\f, \\n, \\r, \\s, \\t):","rawContent":"{{sudo dmesg}} | yank"},{"id":130,"programId":28,"title":"Yank an entire line:","rawContent":"{{sudo dmesg}} | yank -l"},{"id":131,"programId":28,"title":"Yank using a specific delimiter:","rawContent":"{{echo hello=world}} | yank -d {{=}}"},{"id":132,"programId":28,"title":"Only yank fields matching a specific pattern:","rawContent":"{{ps ux}} | yank -g {{\"[0-9]+\"}}"},{"id":133,"programId":29,"title":"List all commands that you could run:","rawContent":"compgen -c"},{"id":134,"programId":29,"title":"List all aliases:","rawContent":"compgen -a"},{"id":135,"programId":29,"title":"List all functions that you could run:","rawContent":"compgen -A function"},{"id":136,"programId":29,"title":"Show shell reserved key words:","rawContent":"compgen -k"},{"id":137,"programId":29,"title":"See all available commands/aliases starting with 'ls':","rawContent":"compgen -ac {{ls}}"},{"id":138,"programId":30,"title":"Call `echo` with the \"foo\" argument:","rawContent":"eval \"{{echo foo}}\""},{"id":139,"programId":30,"title":"Set a variable in the current shell:","rawContent":"eval \"{{foo=bar}}\""},{"id":140,"programId":31,"title":"Print the hexadecimal representation of a file:","rawContent":"hexdump {{file}}"},{"id":141,"programId":31,"title":"Display the input offset in hexadecimal and its ASCII representation in two columns:","rawContent":"hexdump -C {{file}}"},{"id":142,"programId":31,"title":"Display the hexadecimal representation of a file, but interpret only n bytes of the input:","rawContent":"hexdump -C -n{{number_of_bytes}} {{file}}"},{"id":143,"programId":32,"title":"Check all files in the current directory (including subdirectories):","rawContent":"rubocop"},{"id":144,"programId":32,"title":"Check one or more specific files or directories:","rawContent":"rubocop {{path/to/file}} {{path/to/directory}}"},{"id":145,"programId":32,"title":"Write output to file:","rawContent":"rubocop --out {{path/to/file}}"},{"id":146,"programId":32,"title":"View list of cops (linter rules):","rawContent":"rubocop --show-cops"},{"id":147,"programId":32,"title":"Exclude a cop:","rawContent":"rubocop --except {{cop_1}} {{cop_2}}"},{"id":148,"programId":32,"title":"Run only specified cops:","rawContent":"rubocop --only {{cop_1}} {{cop_2}}"},{"id":149,"programId":32,"title":"Auto-correct files (experimental):","rawContent":"rubocop --auto-correct"},{"id":150,"programId":33,"title":"Specify an output directory so that originals do not get modified:","rawContent":"sips --out {{path/to/out_dir}}"},{"id":151,"programId":33,"title":"Resample image at specified size, Image aspect ratio may be altered:","rawContent":"sips -z {{1920}} {{300}} {{image.ext}}"},{"id":152,"programId":33,"title":"Resample image so height and width aren't greater than specified size (notice the capital Z):","rawContent":"sips -Z {{1920}} {{300}} {{image.ext}}"},{"id":153,"programId":33,"title":"Resample all images in a folder to fit a width of 960px (honoring aspect ratio):","rawContent":"sips --resampleWidth {{960}} {{path/to/images}}"},{"id":154,"programId":33,"title":"Convert an image from CMYK to RGB:","rawContent":"sips --matchTo '/System/Library/ColorSync/Profiles/Generic RGB Profile.icc' {{path/to/image.ext}} {{path/to/out_dir}}"},{"id":155,"programId":33,"title":"Remove ColorSync ICC profile from an image:","rawContent":"sips -d profile --deleteColorManagementProperties {{path/to/image.ext}}"},{"id":156,"programId":34,"title":"Run in interactive mode:","rawContent":"units"},{"id":157,"programId":34,"title":"Show the conversion between two simple units:","rawContent":"units {{quarts}} {{tablespoons}}"},{"id":158,"programId":34,"title":"Convert between units with quantities:","rawContent":"units {{15 pounds}} {{kilograms}}"},{"id":159,"programId":34,"title":"Show the conversion between two compound units:","rawContent":"units {{\"meters / second\"}} {{\"inches / hour\"}}"},{"id":160,"programId":34,"title":"Show the conversion between units with different dimensions:","rawContent":"units {{\"acres\"}} {{\"ft^2\"}}"},{"id":161,"programId":35,"title":"Yank using the default delimiters (\\f, \\n, \\r, \\s, \\t):","rawContent":"{{sudo dmesg}} | yank"},{"id":162,"programId":35,"title":"Yank an entire line:","rawContent":"{{sudo dmesg}} | yank -l"},{"id":163,"programId":35,"title":"Yank using a specific delimiter:","rawContent":"{{echo hello=world}} | yank -d {{=}}"},{"id":164,"programId":35,"title":"Only yank fields matching a specific pattern:","rawContent":"{{ps ux}} | yank -g {{\"[0-9]+\"}}"},{"id":165,"programId":36,"title":"Display a list of available features:","rawContent":"choco feature list"},{"id":166,"programId":36,"title":"Enable a feature:","rawContent":"choco feature enable --name {{name}}"},{"id":167,"programId":36,"title":"Disable a feature:","rawContent":"choco feature disable --name {{name}}"},{"id":168,"programId":37,"title":"Display information on a specific package:","rawContent":"choco info {{package}}"},{"id":169,"programId":37,"title":"Display information for a local package only:","rawContent":"choco info {{package}} --local-only"},{"id":170,"programId":37,"title":"Specify a custom source to receive packages information from:","rawContent":"choco info {{package}} --source {{source_url|alias}}"},{"id":171,"programId":37,"title":"Provide a username and password for authentication:","rawContent":"choco info {{package}} --user {{username}} --password {{password}}"},{"id":172,"programId":38,"title":"Install one or more space-separated packages:","rawContent":"choco install {{package(s)}}"},{"id":173,"programId":38,"title":"Install packages from a custom configuration file:","rawContent":"choco install {{path/to/packages.config}}"},{"id":174,"programId":38,"title":"Install a specific \"nuspec\" or \"nupkg\" file:","rawContent":"choco install {{path/to/file}}"},{"id":175,"programId":38,"title":"Install a specific version of a package:","rawContent":"choco install {{package}} --version {{version}}"},{"id":176,"programId":38,"title":"Allow installing multiple versions of a package:","rawContent":"choco install {{package}} --allow-multiple"},{"id":177,"programId":38,"title":"Confirm all prompts automatically:","rawContent":"choco install {{package}} --yes"},{"id":178,"programId":38,"title":"Specify a custom source to receive packages from:","rawContent":"choco install {{package}} --source {{source_url|alias}}"},{"id":179,"programId":38,"title":"Provide a username and password for authentication:","rawContent":"choco install {{package}} --user {{username}} --password {{password}}"},{"id":180,"programId":39,"title":"Display all available packages:","rawContent":"choco list"},{"id":181,"programId":39,"title":"Display all locally installed packages:","rawContent":"choco list --local-only"},{"id":182,"programId":39,"title":"Display a list including local programs:","rawContent":"choco list --include-programs"},{"id":183,"programId":39,"title":"Display only approved packages:","rawContent":"choco list --approved-only"},{"id":184,"programId":39,"title":"Specify a custom source to display packages from:","rawContent":"choco list --source {{source_url|alias}}"},{"id":185,"programId":39,"title":"Provide a username and password for authentication:","rawContent":"choco list --user {{username}} --password {{password}}"},{"id":186,"programId":40,"title":"Create a new package skeleton:","rawContent":"choco new {{package_name}}"},{"id":187,"programId":40,"title":"Create a new package with a specific version:","rawContent":"choco new {{package_name}} --version {{version}}"},{"id":188,"programId":40,"title":"Create a new package with a specific maintainer name:","rawContent":"choco new {{package_name}} --maintainer {{maintainer_name}}"},{"id":189,"programId":40,"title":"Create a new package in a custom output directory:","rawContent":"choco new {{package_name}} --output-directory {{path/to/directory}}"},{"id":190,"programId":40,"title":"Create a new package with specific 32-bit and 64-bit installer urls:","rawContent":"choco new {{package_name}} url=\"{{url}}\" url64=\"{{url}}\""},{"id":191,"programId":41,"title":"Display a list of outdated packages in table format:","rawContent":"choco outdated"},{"id":192,"programId":41,"title":"Ignore pinned packages in the output:","rawContent":"choco outdated --ignore-pinned"},{"id":193,"programId":41,"title":"Specify a custom source to check packages from:","rawContent":"choco outdated --source {{source_url|alias}}"},{"id":194,"programId":41,"title":"Provide a username and password for authentication:","rawContent":"choco outdated --user {{username}} --password {{password}}"},{"id":195,"programId":42,"title":"Display a list of pinned packages and their versions:","rawContent":"choco pin list"},{"id":196,"programId":42,"title":"Pin a package at its current version:","rawContent":"choco pin add --name {{package}}"},{"id":197,"programId":42,"title":"Pin a package at a specific version:","rawContent":"choco pin add --name {{package}} --version {{version}}"},{"id":198,"programId":42,"title":"Remove a pin for a specific package:","rawContent":"choco pin remove --name {{package}}"},{"id":199,"programId":43,"title":"Search for a package:","rawContent":"choco search {{query}}"},{"id":200,"programId":43,"title":"Search for a package locally:","rawContent":"choco search {{query}} --local-only"},{"id":201,"programId":43,"title":"Only include exact matches in the results:","rawContent":"choco search {{query}} --exact"},{"id":202,"programId":43,"title":"Confirm all prompts automatically:","rawContent":"choco search {{query}} --yes"},{"id":203,"programId":43,"title":"Specify a custom source to search for packages in:","rawContent":"choco search {{query}} --source {{source_url|alias}}"},{"id":204,"programId":43,"title":"Provide a username and password for authentication:","rawContent":"choco search {{query}} --user {{username}} --password {{password}}"},{"id":205,"programId":44,"title":"List currently available sources:","rawContent":"choco source list"},{"id":206,"programId":44,"title":"Add a new package source:","rawContent":"choco source add --name {{name}} --source {{url}}"},{"id":207,"programId":44,"title":"Add a new package source with credentials:","rawContent":"choco source add --name {{name}} --source {{url}} --user {{username}} --password {{password}}"},{"id":208,"programId":44,"title":"Add a new package source with a client certificate:","rawContent":"choco source add --name {{name}} --source {{url}} --cert {{path/to/certificate}}"},{"id":209,"programId":44,"title":"Enable a package source:","rawContent":"choco source enable --name {{name}}"},{"id":210,"programId":44,"title":"Disable a package source:","rawContent":"choco source disable --name {{name}}"},{"id":211,"programId":44,"title":"Remove a package source:","rawContent":"choco source remove --name {{name}}"},{"id":212,"programId":45,"title":"Uninstall one or more space-separated packages:","rawContent":"choco uninstall {{package(s)}}"},{"id":213,"programId":45,"title":"Uninstall a specific version of a package:","rawContent":"choco uninstall {{package}} --version {{version}}"},{"id":214,"programId":45,"title":"Confirm all prompts automatically:","rawContent":"choco uninstall {{package}} --yes"},{"id":215,"programId":45,"title":"Remove all dependencies when uninstalling:","rawContent":"choco uninstall {{package}} --remove-dependencies"},{"id":216,"programId":45,"title":"Uninstall all packages:","rawContent":"choco uninstall all"},{"id":217,"programId":46,"title":"Upgrade one or more space-separated packages:","rawContent":"choco upgrade {{package(s)}}"},{"id":218,"programId":46,"title":"Upgrade to a specific version of a package:","rawContent":"choco upgrade {{package}} --version {{version}}"},{"id":219,"programId":46,"title":"Upgrade all packages:","rawContent":"choco upgrade all"},{"id":220,"programId":46,"title":"Upgrade all except specified comma-separated packages:","rawContent":"choco upgrade all --except \"{{package(s)}}\""},{"id":221,"programId":46,"title":"Confirm all prompts automatically:","rawContent":"choco upgrade {{package}} --yes"},{"id":222,"programId":46,"title":"Specify a custom source to receive packages from:","rawContent":"choco upgrade {{package}} --source {{source_url|alias}}"},{"id":223,"programId":46,"title":"Provide a username and password for authentication:","rawContent":"choco upgrade {{package}} --user {{username}} --password {{password}}"},{"id":224,"programId":47,"title":"Execute Chocolatey command:","rawContent":"choco {{command}}"},{"id":225,"programId":47,"title":"Call general help:","rawContent":"choco -?"},{"id":226,"programId":47,"title":"Call help on a specific command:","rawContent":"choco {{command}} -?"},{"id":227,"programId":47,"title":"Check the Chocolatey version:","rawContent":"choco --version"},{"id":228,"programId":48,"title":"Delete one or more space-separated files or patterns:","rawContent":"del {{file_pattern}}"},{"id":229,"programId":48,"title":"Prompt for confirmation before deleting each file:","rawContent":"del {{file_pattern}} /p"},{"id":230,"programId":48,"title":"Force the deletion of read-only files:","rawContent":"del {{file_pattern}} /f"},{"id":231,"programId":48,"title":"Recursively delete file(s) from all subdirectories:","rawContent":"del {{file_pattern}} /s"},{"id":232,"programId":48,"title":"Do not prompt when deleting files based on a global wildcard:","rawContent":"del {{file_pattern}} /q"},{"id":233,"programId":48,"title":"Display the help and list available attributes:","rawContent":"del /?"},{"id":234,"programId":48,"title":"Delete files based on specified attributes:","rawContent":"del {{file_pattern}} /a {{attribute}}"},{"id":235,"programId":49,"title":"Run in interactive mode:","rawContent":"units"},{"id":236,"programId":49,"title":"Show the conversion between two simple units:","rawContent":"units {{quarts}} {{tablespoons}}"},{"id":237,"programId":49,"title":"Convert between units with quantities:","rawContent":"units {{15 pounds}} {{kilograms}}"},{"id":238,"programId":49,"title":"Show the conversion between two compound units:","rawContent":"units {{\"meters / second\"}} {{\"inches / hour\"}}"},{"id":239,"programId":49,"title":"Show the conversion between units with different dimensions:","rawContent":"units {{\"acres\"}} {{\"ft^2\"}}"}]